{
  "pass": 25,
  "factory": "loops\\forward-015\\factory-eco-01-opus",
  "results": [
    {
      "actual": "201 id=bk_a5595610d7f44bd7b309277b3576509f avail=2",
      "pass": true,
      "id": "S01",
      "expected": "201 bk_* copies=2 avail=2"
    },
    {
      "actual": "201 id=mb_ea2e5676499d4297a258f0a51ec335dc",
      "pass": true,
      "id": "S02",
      "expected": "201 mb_*"
    },
    {
      "actual": "400/invalid_request",
      "pass": true,
      "id": "S03",
      "expected": "400/invalid_request"
    },
    {
      "actual": "404/not_found",
      "pass": true,
      "id": "S04",
      "expected": "404/not_found"
    },
    {
      "actual": "201 due=2026-02-14 status=active",
      "pass": true,
      "id": "S05",
      "expected": "201 due=2026-02-14 active"
    },
    {
      "actual": "2nd=201 3rd=409/no_copies_available",
      "pass": true,
      "id": "S06",
      "expected": "2nd=201, 3rd=409/no_copies_available"
    },
    {
      "actual": "1-3=201,201,201 4th=409/loan_limit_exceeded",
      "pass": true,
      "id": "S07",
      "expected": "3rd=201, 4th=409/loan_limit_exceeded"
    },
    {
      "actual": "400/invalid_request",
      "pass": true,
      "id": "S08",
      "expected": "400/invalid_request (+09:00)"
    },
    {
      "actual": "400/invalid_request",
      "pass": true,
      "id": "S09",
      "expected": "400/invalid_request (+00:00)"
    },
    {
      "actual": "201",
      "pass": true,
      "id": "S10",
      "expected": "201 (.123Z accepted)"
    },
    {
      "actual": "200 fine=0",
      "pass": true,
      "id": "S11",
      "expected": "200 fine=0 (due-day 23:59:59Z)"
    },
    {
      "actual": "200 fine=100",
      "pass": true,
      "id": "S12",
      "expected": "200 fine=100 (due+1 00:00:00Z)"
    },
    {
      "actual": "200 fine=300",
      "pass": true,
      "id": "S13",
      "expected": "200 fine=300 (due+3)"
    },
    {
      "actual": "409/already_returned",
      "pass": true,
      "id": "S14",
      "expected": "409/already_returned"
    },
    {
      "actual": "409/member_overdue_blocked",
      "pass": true,
      "id": "S15",
      "expected": "409/member_overdue_blocked (due+1)"
    },
    {
      "actual": "201",
      "pass": true,
      "id": "S16",
      "expected": "201 (due-day not blocked)"
    },
    {
      "actual": "400/invalid_request",
      "pass": true,
      "id": "S17",
      "expected": "400/invalid_request (instant past)"
    },
    {
      "actual": "count=3 order=True shape=True",
      "pass": true,
      "id": "S18",
      "expected": "order(oldest,id-ordinal) + shape"
    },
    {
      "actual": "checked=3 bad=",
      "pass": true,
      "id": "S21",
      "expected": "prefix + 32 lowercase hex"
    },
    {
      "actual": "S05=2026-01-31T10:00:00Z S10=2026-03-02T09:00:00Z",
      "pass": true,
      "id": "S22",
      "expected": "S05=2026-01-31T10:00:00Z / S10=2026-03-02T09:00:00Z (exact)"
    },
    {
      "actual": "bookId='' 400/invalid_request / memberId='   ' 400/invalid_request / ?memberId= 400/invalid_request",
      "pass": true,
      "id": "S23",
      "expected": "empty/whitespace ids and ?memberId= all 400/invalid_request"
    },
    {
      "actual": "prem=201/premium def=201/standard bad=400/invalid_request",
      "pass": true,
      "id": "S24",
      "expected": "premium=201/premium, default=201/standard, gold=400"
    },
    {
      "actual": "1-5ok=True 6th=409/loan_limit_exceeded",
      "pass": true,
      "id": "S25",
      "expected": "1-5=201, 6th=409/loan_limit_exceeded"
    },
    {
      "actual": "premA=201/2026-02-14 premB=201/2027-01-08 std=201/2026-02-14",
      "pass": false,
      "id": "S26",
      "expected": "premium 1/31->2026-02-21, 12/25->2027-01-15 / standard対照 1/31->2026-02-14"
    },
    {
      "actual": "t1=200/fine=700 t2=200/fine=800",
      "pass": false,
      "id": "S27",
      "expected": "premium due-day(+21) 23:59:59Z=0 / due+1 00:00:00Z=100"
    },
    {
      "actual": "u1=201 u2=409 u3=409/member_overdue_blocked",
      "pass": false,
      "id": "S28",
      "expected": "due-day(+21)=201 / due+1=409 member_overdue_blocked"
    },
    {
      "actual": "avail 0->0 loans 3->3 ids-equal=True",
      "pass": true,
      "id": "S19",
      "expected": "restart-survives (avail/loans/status equal)"
    },
    {
      "actual": "median=6.1ms n=50",
      "pass": true,
      "id": "S20",
      "expected": "median<300ms over 50 seq POST"
    }
  ],
  "total": 28,
  "oracle": "fixed oracle S01-S28 (rev4/ECO-002)",
  "probes": {
    "latencyMs": 6.1,
    "errorMessages": [
      "title is required and must be 1..200 chars",
      "resource not found"
    ],
    "ids": [
      "bk_a5595610d7f44bd7b309277b3576509f",
      "mb_ea2e5676499d4297a258f0a51ec335dc",
      "ln_f1e3eb420fac427c94be7a262bd1e599"
    ],
    "datetimeEcho": [
      "2026-01-31T10:00:00Z",
      "2026-03-02T09:00:00Z"
    ],
    "extraFields": {}
  }
}
